pytest_greener/__init__.py
pytest_greener/plugin.py
pytest_greener-1.2.0.dist-info/METADATA
pytest_greener-1.2.0.dist-info/WHEEL
pytest_greener-1.2.0.dist-info/entry_points.txt
pytest_greener-1.2.0.dist-info/licenses/LICENSE
pytest_greener-1.2.0.dist-info/RECORD
