Metadata-Version: 2.4
Name: pytest-greener
Version: 1.2.0
Summary: Pytest plugin for Greener
License-File: LICENSE
Author: cephei8
Requires-Python: >=3.8,<4.0
Classifier: Programming Language :: Python :: 3
Classifier: Programming Language :: Python :: 3.8
Classifier: Programming Language :: Python :: 3.9
Classifier: Programming Language :: Python :: 3.10
Classifier: Programming Language :: Python :: 3.11
Classifier: Programming Language :: Python :: 3.12
Classifier: Programming Language :: Python :: 3.13
Classifier: Programming Language :: Python :: 3.14
Requires-Dist: greener-reporter (==1.3.0)
Requires-Dist: pytest (>=8.3.3,<9.0.0)
